critical_es_value/__init__.py
critical_es_value/corrtest.py
critical_es_value/linreg.py
critical_es_value/ttest.py
critical_es_value/utils.py
critical_es_value-0.4.1.dist-info/METADATA
critical_es_value-0.4.1.dist-info/WHEEL
critical_es_value-0.4.1.dist-info/licenses/LICENSE
critical_es_value-0.4.1.dist-info/RECORD
