Metadata-Version: 2.4
Name: critical-es-value
Version: 0.4.1
Summary: Calculate critical effect size values.
Project-URL: Repository, https://github.com/r0f1/critical_es_value
Project-URL: Documentation, https://r0f1.github.io/critical_es_value/
Project-URL: Homepage, https://r0f1.github.io/critical_es_value/
Author-email: Florian Rohrer <semicolonator@gmail.com>
License-File: LICENSE
Requires-Python: >=3.11
Requires-Dist: mpmath>=1.3.0
Requires-Dist: pandas>=2.3.3
Requires-Dist: pingouin>=0.5.5
